ThreadFixProApi/__init__.py
ThreadFixProApi/threadfixpro.py
_utils/__init__.py
_utils/_application.py
_utils/_cicd.py
_utils/_defect_trackers.py
_utils/_email_reporting.py
_utils/_miscellaneous.py
_utils/_policies.py
_utils/_remote_providers.py
_utils/_scans.py
_utils/_tags.py
_utils/_tasks.py
_utils/_team.py
_utils/_users_roles_and_groups.py
_utils/_utilities.py
_utils/_vulnerabilities.py
_utils/_waf.py
ThreadFixProAPI-1.0.13.dist-info/LICENSE.txt
ThreadFixProAPI-1.0.13.dist-info/METADATA
ThreadFixProAPI-1.0.13.dist-info/WHEEL
ThreadFixProAPI-1.0.13.dist-info/top_level.txt
ThreadFixProAPI-1.0.13.dist-info/RECORD
