Metadata-Version: 2.1
Name: ThreadFixProAPI
Version: 1.0.13
Summary: UNKNOWN
Home-page: UNKNOWN
License: MIT
Platform: UNKNOWN
